pypi_test.py
sub_package/__init__.py
sub_package/sub.py
pypi_test_lib-1.0.0.dist-info/LICENSE.txt
pypi_test_lib-1.0.0.dist-info/METADATA
pypi_test_lib-1.0.0.dist-info/WHEEL
pypi_test_lib-1.0.0.dist-info/top_level.txt
pypi_test_lib-1.0.0.dist-info/RECORD
