Metadata-Version: 2.1
Name: pypi-test-lib
Version: 1.0.0
Summary: This is a test lib.
Author: sz
Author-email: xixihaha@qq.com
License: MIT
License-File: LICENSE.txt
